MANIFEST.in
README.md
rabk.py
setup.py
rabk.egg-info/PKG-INFO
rabk.egg-info/SOURCES.txt
rabk.egg-info/dependency_links.txt
rabk.egg-info/requires.txt
rabk.egg-info/top_level.txt