Metadata-Version: 2.1
Name: rabk
Version: 0.1
Summary: A package that generates bills
Author: Belajdel rabek 
Author-email: belajdelmedamine@gmail.com
